LICENSE
logbook_cli/__init__.py
logbook_cli/__main__.py
logbook_cli/cli.py
logbook_cli/managers.py
logbook_cli/models.py
logbook_cli/utils.py
logbook_cli-0.5.2.dist-info/entry_points.txt
logbook_cli-0.5.2.dist-info/LICENSE
logbook_cli-0.5.2.dist-info/WHEEL
logbook_cli-0.5.2.dist-info/METADATA
logbook_cli-0.5.2.dist-info/RECORD
