Metadata-Version: 2.1
Name: logbook-cli
Version: 0.5.2
Summary: Keep Your Daily Events Recorded on Your Logbook Using Command Line.
Home-page: https://github.com/saadmk11/logbook-cli
License: MIT
Author: Maksudul Haque
Author-email: saad.mk112@gmail.com
Requires-Python: >=3.6,<4.0
Classifier: License :: OSI Approved :: MIT License
Classifier: Programming Language :: Python :: 3
Classifier: Programming Language :: Python :: 3.6
Classifier: Programming Language :: Python :: 3.7
Classifier: Programming Language :: Python :: 3.8
Classifier: Programming Language :: Python :: 3.9
Requires-Dist: SQLAlchemy (==1.4.15)
Requires-Dist: colorama (==0.4.4)
Requires-Dist: shellingham (==1.4.0)
Requires-Dist: tabulate (==0.8.9)
Requires-Dist: typer (==0.3.2)
Project-URL: Repository, https://github.com/saadmk11/logbook-cli
